deeply_nested/__init__.py
deeply_nested/nested_object.py
deeply_nested-0.0.2.dist-info/LICENSE
deeply_nested-0.0.2.dist-info/METADATA
deeply_nested-0.0.2.dist-info/WHEEL
deeply_nested-0.0.2.dist-info/top_level.txt
deeply_nested-0.0.2.dist-info/RECORD
